{
	"configurations" : 
	[
		{
			"directories" : 
			[
				{
					"build" : ".",
					"jsonFile" : "directory-.-Debug-f5ebdc15457944623624.json",
					"minimumCMakeVersion" : 
					{
						"string" : "3.22"
					},
					"projectIndex" : 0,
					"source" : ".",
					"targetIndexes" : 
					[
						0
					]
				}
			],
			"name" : "Debug",
			"projects" : 
			[
				{
					"directoryIndexes" : 
					[
						0
					],
					"name" : "1_2011_42",
					"targetIndexes" : 
					[
						0
					]
				}
			],
			"targets" : 
			[
				{
					"directoryIndex" : 0,
					"id" : "1_2011_42::@6890427a1f51a3e7e1df",
					"jsonFile" : "target-1_2011_42-Debug-9a07ef84a7827da485c3.json",
					"name" : "1_2011_42",
					"projectIndex" : 0
				}
			]
		}
	],
	"kind" : "codemodel",
	"paths" : 
	{
		"build" : "/cygdrive/c/c\u8bed\u8a00/1/15.7/1-2011-42/cmake-build-debug",
		"source" : "/cygdrive/c/c\u8bed\u8a00/1/15.7/1-2011-42"
	},
	"version" : 
	{
		"major" : 2,
		"minor" : 3
	}
}
